eocharging/ChargingData.py
eocharging/Device.py
eocharging/Helpers.py
eocharging/Manager.py
eocharging/__init__.py
pyEOCharging-0.0.7.dist-info/METADATA
pyEOCharging-0.0.7.dist-info/WHEEL
pyEOCharging-0.0.7.dist-info/top_level.txt
pyEOCharging-0.0.7.dist-info/RECORD
