Metadata-Version: 2.1
Name: pyEOCharging
Version: 0.0.7
Summary: EO Smart Charger Library
Home-page: https://github.com/bfayers/pyEOCharging
Author: bfayers
License: GPLv3
Project-URL: Bug Tracker, https://github.com/bfayers/pyEOCharging/issues
Requires-Dist: requests>=2.25.1
